{
  "id": "经济法/反食品浪费法",
  "title": "中华人民共和国反食品浪费法",
  "description": "2021年4月29日 第十三届全国人民代表大会常务委员会第二十八次会议通过",
  "source": "@site/google/经济法/反食品浪费法.md",
  "sourceDirName": "经济法",
  "slug": "/经济法/反食品浪费法",
  "permalink": "/google/经济法/反食品浪费法",
  "draft": false,
  "unlisted": false,
  "editUrl": "https://github.com/teabagging/security/edit/main/website/google/经济法/反食品浪费法.md",
  "tags": [],
  "version": "current",
  "frontMatter": {},
  "sidebar": "devDocsSidebar",
  "previous": {
    "title": "中华人民共和国反洗钱法",
    "permalink": "/google/经济法/反洗钱法"
  },
  "next": {
    "title": "中华人民共和国可再生能源法",
    "permalink": "/google/经济法/可再生能源法"
  }
}