{
  "id": "行政法规/行政区域界线管理条例",
  "title": "行政区域界线管理条例",
  "description": "2002年5月13日 中华人民共和国国务院令第353号公布",
  "source": "@site/google/行政法规/行政区域界线管理条例.md",
  "sourceDirName": "行政法规",
  "slug": "/行政法规/行政区域界线管理条例",
  "permalink": "/google/行政法规/行政区域界线管理条例",
  "draft": false,
  "unlisted": false,
  "editUrl": "https://github.com/teabagging/security/edit/main/website/google/行政法规/行政区域界线管理条例.md",
  "tags": [],
  "version": "current",
  "frontMatter": {},
  "sidebar": "devDocsSidebar",
  "previous": {
    "title": "行政区划管理条例",
    "permalink": "/google/行政法规/行政区划管理条例"
  },
  "next": {
    "title": "行政区域边界争议处理条例",
    "permalink": "/google/行政法规/行政区域边界争议处理条例"
  }
}