{
  "id": "司法解释/关于严格执行案件审理期限制度的若干规定",
  "title": "最高人民法院关于严格执行案件审理期限制度的若干规定",
  "description": "2000年9月14日 最高人民法院审判委员会第1130次会议通过",
  "source": "@site/google/司法解释/关于严格执行案件审理期限制度的若干规定.md",
  "sourceDirName": "司法解释",
  "slug": "/司法解释/关于严格执行案件审理期限制度的若干规定",
  "permalink": "/google/司法解释/关于严格执行案件审理期限制度的若干规定",
  "draft": false,
  "unlisted": false,
  "editUrl": "https://github.com/teabagging/security/edit/main/website/google/司法解释/关于严格执行案件审理期限制度的若干规定.md",
  "tags": [],
  "version": "current",
  "frontMatter": {},
  "sidebar": "devDocsSidebar",
  "previous": {
    "title": "最高人民法院关于上海金融法院案件管辖的规定",
    "permalink": "/google/司法解释/关于上海金融法院案件管辖的规定"
  },
  "next": {
    "title": "最高人民法院关于严格规范民商事案件延长审限和延期开庭问题的规定",
    "permalink": "/google/司法解释/关于严格规范民商事案件延长审限和延期开庭问题的规定"
  }
}