{
  "id": "行政法/社区矫正法",
  "title": "中华人民共和国社区矫正法",
  "description": "2019年12月28日 第十三届全国人民代表大会常务委员会第十五次会议通过",
  "source": "@site/google/行政法/社区矫正法.md",
  "sourceDirName": "行政法",
  "slug": "/行政法/社区矫正法",
  "permalink": "/google/行政法/社区矫正法",
  "draft": false,
  "unlisted": false,
  "editUrl": "https://github.com/teabagging/security/edit/main/website/google/行政法/社区矫正法.md",
  "tags": [],
  "version": "current",
  "frontMatter": {},
  "sidebar": "devDocsSidebar",
  "previous": {
    "title": "中华人民共和国监狱法",
    "permalink": "/google/行政法/监狱法"
  },
  "next": {
    "title": "中华人民共和国禁毒法",
    "permalink": "/google/行政法/禁毒法"
  }
}