{
  "id": "经济法/建筑法",
  "title": "中华人民共和国建筑法",
  "description": "1997年11月1日 第八届全国人民代表大会常务委员会第二十八次会议通过",
  "source": "@site/google/经济法/建筑法.md",
  "sourceDirName": "经济法",
  "slug": "/经济法/建筑法",
  "permalink": "/google/经济法/建筑法",
  "draft": false,
  "unlisted": false,
  "editUrl": "https://github.com/teabagging/security/edit/main/website/google/经济法/建筑法.md",
  "tags": [],
  "version": "current",
  "frontMatter": {},
  "sidebar": "devDocsSidebar",
  "previous": {
    "title": "中华人民共和国广告法",
    "permalink": "/google/经济法/广告法"
  },
  "next": {
    "title": "中华人民共和国循环经济促进法",
    "permalink": "/google/经济法/循环经济促进法"
  }
}